d_treevis/__init__.py
d_treevis/decision_tree_vis.py
decision_tree_visualizer-1.0.0.dist-info/licenses/LICENSE
decision_tree_visualizer-1.0.0.dist-info/METADATA
decision_tree_visualizer-1.0.0.dist-info/WHEEL
decision_tree_visualizer-1.0.0.dist-info/top_level.txt
decision_tree_visualizer-1.0.0.dist-info/RECORD
